instarex/__init__.py
instarex/singleton.py
instarex/utils.py
instarex/api/__init__.py
instarex/api/api.py
instarex/api/api_login.py
instarex/api/api_photo.py
instarex/api/api_story.py
instarex/api/api_video.py
instarex/api/config.py
instarex/api/devices.py
instarex/api/prepare.py
instarex/bot/__init__.py
instarex/bot/bot.py
instarex/bot/bot_archive.py
instarex/bot/bot_block.py
instarex/bot/bot_checkpoint.py
instarex/bot/bot_comment.py
instarex/bot/bot_delete.py
instarex/bot/bot_direct.py
instarex/bot/bot_filter.py
instarex/bot/bot_follow.py
instarex/bot/bot_get.py
instarex/bot/bot_like.py
instarex/bot/bot_photo.py
instarex/bot/bot_stats.py
instarex/bot/bot_story.py
instarex/bot/bot_support.py
instarex/bot/bot_unfollow.py
instarex/bot/bot_unlike.py
instarex/bot/bot_video.py
instarex/bot/state/__init__.py
instarex/bot/state/bot_cache.py
instarex/bot/state/bot_state.py
instarex-0.120.0.dist-info/LICENSE
instarex-0.120.0.dist-info/METADATA
instarex-0.120.0.dist-info/WHEEL
instarex-0.120.0.dist-info/top_level.txt
instarex-0.120.0.dist-info/RECORD
