Metadata-Version: 2.1
Name: instarex
Version: 0.120.0
Summary: Develop Instagram bots with ease!
Home-page: https://github.com/reala10n/instarex
Author: Alon Krymgand, Daniil Okhlopkov, Evgeny Kemerov
Author-email: downtown2u@gmail.com, danokhlopkov@gmail.com, eskemerov@gmail.com
License: Apache Software License 2.0
Keywords: instagram,uploader,bot,api,wrapper
Platform: UNKNOWN
Classifier: Development Status :: 4 - Beta
Classifier: Intended Audience :: Information Technology
Classifier: License :: OSI Approved :: Apache Software License
Classifier: Programming Language :: Python :: 3
Classifier: Programming Language :: Python :: 3.6
Classifier: Programming Language :: Python :: 3.7
Classifier: Programming Language :: Python :: 3.8
Classifier: Programming Language :: Python :: 3.9
License-File: LICENSE
Requires-Dist: certifi (>=2019.11.28)
Requires-Dist: chardet (>=3.0.4)
Requires-Dist: future (>=0.18.2)
Requires-Dist: huepy (>=1.2.1)
Requires-Dist: idna (>=2.8)
Requires-Dist: pysocks (>=1.7.1)
Requires-Dist: pytz (>=2019.3)
Requires-Dist: requests (>=2.22.0)
Requires-Dist: requests-toolbelt (>=0.9.1)
Requires-Dist: responses (>=0.10.9)
Requires-Dist: schedule (>=0.6.0)
Requires-Dist: six (>=1.14.0)
Requires-Dist: rsa (>=4.7.0)
Requires-Dist: tqdm (>=4.41.1)
Requires-Dist: urllib3 (>=1.25.7)
Requires-Dist: mock (>=3.0.5)
Requires-Dist: moviepy (>=1.0.1)
Requires-Dist: Pillow (>=6.2.2)
Requires-Dist: pytest (>=4.6.9)
Requires-Dist: pycryptodome (>=3.9.7)
